scipy_optimstruct/__init__.py
scipy_optimstruct/optimstruct.py
scipy_optimstruct-0.1.3.dist-info/LICENSE.txt
scipy_optimstruct-0.1.3.dist-info/METADATA
scipy_optimstruct-0.1.3.dist-info/WHEEL
scipy_optimstruct-0.1.3.dist-info/top_level.txt
scipy_optimstruct-0.1.3.dist-info/RECORD
