Metadata-Version: 2.1
Name: scipy-optimstruct
Version: 0.1.3
Summary: Enable easier organization of variables and constraints for Scipy Optimize
Home-page: https://github.com/andrewnyu/scipy-optimstruct
Download-URL: https://github.com/andrewnyu/scipy-optimstruct/archive/refs/tags/v0.1.tar.gz
Author: Andrew Yu
Author-email: andrewthomasyu@gmail.com
License: MIT
Keywords: scipy,optimization,data structures
Classifier: Development Status :: 3 - Alpha
Classifier: Intended Audience :: Developers
Classifier: Topic :: Software Development :: Build Tools
Classifier: License :: OSI Approved :: MIT License
Classifier: Programming Language :: Python :: 3
Classifier: Programming Language :: Python :: 3.6
Classifier: Programming Language :: Python :: 3.8
Requires-Python: >=3.6
License-File: LICENSE.txt
Requires-Dist: numpy
Requires-Dist: scipy
